repository_manager/__init__.py
repository_manager/__main__.py
repository_manager/mcp_config.json
repository_manager/middlewares.py
repository_manager/models.py
repository_manager/repositories-list.txt
repository_manager/repository_manager.py
repository_manager/repository_manager_agent.py
repository_manager/repository_manager_mcp.py
repository_manager/utils.py
repository_manager/skills/documentation/SKILL.md
repository_manager/skills/git-advanced/SKILL.md
repository_manager/skills/git-advanced/debug-bisect.md
repository_manager/skills/git-branch-merge/SKILL.md
repository_manager/skills/git-branch-merge/troubleshoot-merge.md
repository_manager/skills/git-clone/SKILL.md
repository_manager/skills/git-commit-stage/SKILL.md
repository_manager/skills/git-config/SKILL.md
repository_manager/skills/git-log-history/SKILL.md
repository_manager/skills/git-pull/SKILL.md
repository_manager/skills/git-remote-pull-push/SKILL.md
repository_manager/skills/git-stash/SKILL.md
repository_manager/skills/git-status/SKILL.md
repository_manager/skills/git-status-reset/SKILL.md
repository_manager/skills/git-tag-release/SKILL.md
repository_manager/skills/pre-commit/SKILL.md
repository_manager/skills/project-management/SKILL.md
repository_manager/skills/python-sandbox/SKILL.md
repository_manager/skills/shell/SKILL.md
repository_manager/skills/smart-coding-mcp/SKILL.md
repository_manager/skills/text-editor/SKILL.md
repository_manager-1.2.17.dist-info/licenses/LICENSE
scripts/validate_a2a_agent.py
scripts/validate_agent.py
tests/test_mcp_registration.py
tests/test_repository_manager.py
repository_manager-1.2.17.dist-info/METADATA
repository_manager-1.2.17.dist-info/WHEEL
repository_manager-1.2.17.dist-info/entry_points.txt
repository_manager-1.2.17.dist-info/top_level.txt
repository_manager-1.2.17.dist-info/RECORD
