Metadata-Version: 2.4
Name: repository-manager
Version: 1.2.17
Summary: Manage your git projects
Author-email: Audel Rouhi <knucklessg1@gmail.com>
License: MIT
Classifier: Development Status :: 5 - Production/Stable
Classifier: License :: Public Domain
Classifier: Environment :: Console
Classifier: Operating System :: POSIX :: Linux
Classifier: Programming Language :: Python :: 3
Requires-Python: >=3.10
License-File: LICENSE
Requires-Dist: fastmcp>=3.0.0b1
Provides-Extra: mcp
Requires-Dist: fastmcp>=3.0.0b1; extra == "mcp"
Requires-Dist: eunomia-mcp>=0.3.10; extra == "mcp"
Requires-Dist: fastapi>=0.128.0; extra == "mcp"
Requires-Dist: beautifulsoup4>=4.14.3; extra == "mcp"
Requires-Dist: httpx>=0.28.1; extra == "mcp"
Requires-Dist: mem0-mcp-server>=0.0.1; extra == "mcp"
Provides-Extra: a2a
Requires-Dist: pydantic-ai-slim[a2a,ag-ui,anthropic,fastmcp,google,huggingface,openai,web]>=1.32.0; extra == "a2a"
Requires-Dist: pydantic-ai-skills; extra == "a2a"
Requires-Dist: fastapi>=0.128.0; extra == "a2a"
Requires-Dist: pre-commit>=4.5.1; extra == "a2a"
Requires-Dist: bump2version>=1.0.1; extra == "a2a"
Requires-Dist: mcp-run-python>=0.0.22; extra == "a2a"
Requires-Dist: mem0-mcp-server>=0.0.1; extra == "a2a"
Provides-Extra: gitlab
Requires-Dist: gitlab-api[all]>=25.14.9; extra == "gitlab"
Provides-Extra: all
Requires-Dist: fastmcp>=3.0.0b1; extra == "all"
Requires-Dist: eunomia-mcp>=0.3.10; extra == "all"
Requires-Dist: pydantic-ai-slim[a2a,ag-ui,anthropic,fastmcp,google,huggingface,openai,web]>=1.32.0; extra == "all"
Requires-Dist: pydantic-ai-skills; extra == "all"
Requires-Dist: fastapi>=0.128.0; extra == "all"
Requires-Dist: gitlab-api[all]>=25.14.9; extra == "all"
Requires-Dist: pre-commit>=4.5.1; extra == "all"
Requires-Dist: bump2version>=1.0.1; extra == "all"
Requires-Dist: beautifulsoup4>=4.14.3; extra == "all"
Requires-Dist: httpx>=0.28.1; extra == "all"
Requires-Dist: mcp-run-python>=0.0.22; extra == "all"
Requires-Dist: mem0-mcp-server>=0.0.1; extra == "all"
Dynamic: license-file
